{"objects": [{"class": "gecko", "keypoints": [{"name": "head", "location": [[0, 0, 0]], "projected_location": [[755, 546]]}, {"name": "joint", "location": [[0, 0, 0], [0, 0, 0], [0, 0, 0], [0, 0, 0], [0, 0, 0], [0, 0, 0]], "projected_location": [[803, 517], [697, 563], [733, 481], [702, 417], [674, 357], [649, 443]]}, {"name": "box", "location": [[0, 0, 0], [0, 0, 0], [0, 0, 0], [0, 0, 0], [0, 0, 0], [0, 0, 0]], "projected_location": [[823, 505], [670, 575], [721, 454], [689, 319], [664, 403], [634, 489]]}]}]}