{"objects": [{"class": "gecko", "keypoints": [{"name": "head", "location": [[0, 0, 0]], "projected_location": [[366, 488]]}, {"name": "joint", "location": [[0, 0, 0], [0, 0, 0], [0, 0, 0], [0, 0, 0], [0, 0, 0], [0, 0, 0]], "projected_location": [[344, 544], [410, 411], [423, 510], [499, 491], [546, 532], [535, 432]]}, {"name": "box", "location": [[0, 0, 0], [0, 0, 0], [0, 0, 0], [0, 0, 0], [0, 0, 0], [0, 0, 0]], "projected_location": [[337, 565], [428, 375], [461, 503], [551, 566], [542, 491], [529, 397]]}]}]}