{"objects": [{"class": "gecko", "keypoints": [{"name": "head", "location": [[0, 0, 0]], "projected_location": [[1095, 868]]}, {"name": "joint", "location": [[0, 0, 0], [0, 0, 0], [0, 0, 0], [0, 0, 0], [0, 0, 0], [0, 0, 0]], "projected_location": [[1130, 850], [1029, 886], [1065, 818], [1041, 756], [1050, 700], [985, 755]]}, {"name": "box", "location": [[0, 0, 0], [0, 0, 0], [0, 0, 0], [0, 0, 0], [0, 0, 0], [0, 0, 0]], "projected_location": [[1158, 837], [1008, 902], [1047, 792], [1090, 678], [1022, 726], [948, 770]]}]}]}