{
    "objects": [
        {
            "class": "gecko",
            "keypoints": [
                {
                    "name": "head",
                    "location": [
                        [
                            0,
                            0,
                            0
                        ]
                    ],
                    "projected_location": [
                        [
                            341,
                            378
                        ]
                    ]
                },
                {
                    "name": "joint",
                    "location": [
                        [
                            0,
                            0,
                            0
                        ],
                        [
                            0,
                            0,
                            0
                        ],
                        [
                            0,
                            0,
                            0
                        ],
                        [
                            0,
                            0,
                            0
                        ],
                        [
                            0,
                            0,
                            0
                        ],
                        [
                            0,
                            0,
                            0
                        ]
                    ],
                    "projected_location": [
                        [
                            295,
                            378
                        ],
                        [
                            404,
                            378
                        ],
                        [
                            346,
                            438
                        ],
                        [
                            339,
                            516
                        ],
                        [
                            304,
                            549
                        ],
                        [
                            375,
                            564
                        ]
                    ]
                },
                {
                    "name": "box",
                    "location": [
                        [
                            0,
                            0,
                            0
                        ],
                        [
                            0,
                            0,
                            0
                        ],
                        [
                            0,
                            0,
                            0
                        ],
                        [
                            0,
                            0,
                            0
                        ],
                        [
                            0,
                            0,
                            0
                        ],
                        [
                            0,
                            0,
                            0
                        ]
                    ],
                    "projected_location": [
                        [
                            256,
                            542
                        ],
                        [
                            336,
                            557
                        ],
                        [
                            419,
                            574
                        ],
                        [
                            343,
                            473
                        ],
                        [
                            248,
                            373
                        ],
                        [
                            447,
                            377
                        ]
                    ]
                }
            ]
        }
    ]
}