{
    "objects": [
        {
            "class": "gecko",
            "keypoints": [
                {
                    "name": "head",
                    "location": [
                        [
                            0,
                            0,
                            0
                        ]
                    ],
                    "projected_location": [
                        [
                            328,
                            373
                        ]
                    ]
                },
                {
                    "name": "joint",
                    "location": [
                        [
                            0,
                            0,
                            0
                        ],
                        [
                            0,
                            0,
                            0
                        ],
                        [
                            0,
                            0,
                            0
                        ],
                        [
                            0,
                            0,
                            0
                        ],
                        [
                            0,
                            0,
                            0
                        ],
                        [
                            0,
                            0,
                            0
                        ]
                    ],
                    "projected_location": [
                        [
                            434,
                            539
                        ],
                        [
                            365,
                            506
                        ],
                        [
                            414,
                            487
                        ],
                        [
                            375,
                            419
                        ],
                        [
                            392,
                            338
                        ],
                        [
                            287,
                            397
                        ]
                    ]
                },
                {
                    "name": "box",
                    "location": [
                        [
                            0,
                            0,
                            0
                        ],
                        [
                            0,
                            0,
                            0
                        ],
                        [
                            0,
                            0,
                            0
                        ],
                        [
                            0,
                            0,
                            0
                        ],
                        [
                            0,
                            0,
                            0
                        ],
                        [
                            0,
                            0,
                            0
                        ]
                    ],
                    "projected_location": [
                        [
                            252,
                            418
                        ],
                        [
                            424,
                            319
                        ],
                        [
                            397,
                            454
                        ],
                        [
                            317,
                            488
                        ],
                        [
                            397,
                            517
                        ],
                        [
                            466,
                            561
                        ]
                    ]
                }
            ]
        }
    ]
}