{"objects": [{"class": "gecko", "keypoints": [{"name": "head", "location": [[0, 0, 0]], "projected_location": [[1099, 444]]}, {"name": "joint", "location": [[0, 0, 0], [0, 0, 0], [0, 0, 0], [0, 0, 0], [0, 0, 0], [0, 0, 0]], "projected_location": [[1065, 397], [1077, 506], [1027, 450], [947, 441], [903, 398], [910, 468]]}, {"name": "box", "location": [[0, 0, 0], [0, 0, 0], [0, 0, 0], [0, 0, 0], [0, 0, 0], [0, 0, 0]], "projected_location": [[1063, 365], [1090, 539], [988, 445], [901, 350], [911, 439], [908, 506]]}]}]}