{"objects": [{"class": "gecko", "keypoints": [{"name": "head", "location": [[0, 0, 0]], "projected_location": [[723, 404]]}, {"name": "joint", "location": [[0, 0, 0], [0, 0, 0], [0, 0, 0], [0, 0, 0], [0, 0, 0], [0, 0, 0]], "projected_location": [[802, 397], [676, 403], [740, 334], [781, 244], [810, 199], [737, 226]]}, {"name": "box", "location": [[0, 0, 0], [0, 0, 0], [0, 0, 0], [0, 0, 0], [0, 0, 0], [0, 0, 0]], "projected_location": [[837, 384], [629, 399], [761, 289], [851, 182], [770, 214], [712, 239]]}]}]}