{
    "objects": [
        {
            "class": "gecko",
            "keypoints": [
                {
                    "name": "head",
                    "location": [
                        [
                            0,
                            0,
                            0
                        ]
                    ],
                    "projected_location": [
                        [
                            141,
                            279
                        ]
                    ]
                },
                {
                    "name": "joint",
                    "location": [
                        [
                            0,
                            0,
                            0
                        ],
                        [
                            0,
                            0,
                            0
                        ],
                        [
                            0,
                            0,
                            0
                        ],
                        [
                            0,
                            0,
                            0
                        ],
                        [
                            0,
                            0,
                            0
                        ],
                        [
                            0,
                            0,
                            0
                        ],
                        [
                            0,
                            0,
                            0
                        ],
                        [
                            0,
                            0,
                            0
                        ]
                    ],
                    "projected_location": [
                        [
                            106,
                            350
                        ],
                        [
                            196,
                            214
                        ],
                        [
                            196,
                            312
                        ],
                        [
                            208,
                            202
                        ],
                        [
                            225,
                            324
                        ],
                        [
                            287,
                            358
                        ],
                        [
                            324,
                            289
                        ],
                        [
                            356,
                            400
                        ]
                    ]
                },
                {
                    "name": "box",
                    "location": [
                        [
                            0,
                            0,
                            0
                        ],
                        [
                            0,
                            0,
                            0
                        ],
                        [
                            0,
                            0,
                            0
                        ],
                        [
                            0,
                            0,
                            0
                        ],
                        [
                            0,
                            0,
                            0
                        ],
                        [
                            0,
                            0,
                            0
                        ],
                        [
                            0,
                            0,
                            0
                        ],
                        [
                            0,
                            0,
                            0
                        ]
                    ],
                    "projected_location": [
                        [
                            88,
                            387
                        ],
                        [
                            224,
                            285
                        ],
                        [
                            232,
                            176
                        ],
                        [
                            232,
                            291
                        ],
                        [
                            263,
                            349
                        ],
                        [
                            314,
                            254
                        ],
                        [
                            339,
                            346
                        ],
                        [
                            396,
                            434
                        ]
                    ]
                }
            ]
        }
    ]
}