{
    "objects": [
        {
            "class": "gecko",
            "keypoints": [
                {
                    "name": "head",
                    "location": [
                        [
                            0,
                            0,
                            0
                        ]
                    ],
                    "projected_location": [
                        [
                            141,
                            128
                        ]
                    ]
                },
                {
                    "name": "joint",
                    "location": [
                        [
                            0,
                            0,
                            0
                        ],
                        [
                            0,
                            0,
                            0
                        ],
                        [
                            0,
                            0,
                            0
                        ]
                    ],
                    "projected_location": [
                        [
                            126,
                            186
                        ],
                        [
                            233,
                            161
                        ],
                        [
                            264,
                            213
                        ]
                    ]
                },
                {
                    "name": "box",
                    "location": [
                        [
                            0,
                            0,
                            0
                        ],
                        [
                            0,
                            0,
                            0
                        ],
                        [
                            0,
                            0,
                            0
                        ],
                        [
                            0,
                            0,
                            0
                        ],
                        [
                            0,
                            0,
                            0
                        ],
                        [
                            0,
                            0,
                            0
                        ]
                    ],
                    "projected_location": [
                        [
                            120,
                            200
                        ],
                        [
                            180,
                            72
                        ],
                        [
                            210,
                            154
                        ],
                        [
                            251,
                            216
                        ],
                        [
                            268,
                            164
                        ],
                        [
                            278,
                            112
                        ]
                    ]
                }
            ]
        }
    ]
}